pyzz/__init__.py
pyzz/arithmatic.py
pyzz123/__init__.py
pyzz123/arithmatic.py
pyzz123-1.0.0.dist-info/LICENSE
pyzz123-1.0.0.dist-info/METADATA
pyzz123-1.0.0.dist-info/WHEEL
pyzz123-1.0.0.dist-info/top_level.txt
pyzz123-1.0.0.dist-info/RECORD
